PwmGenerator.v
module pwm_generator(
    input clk,
    input reset,
    input [7:0] duty_cycle,
    output reg pwm_out
);
    reg [7:0] counter;

    always @(posedge clk or posedge reset) begin
        if (reset)
            counter <= 0;
        else
            counter <= counter + 1;
    end

    always @(posedge clk or posedge reset) begin
        if (reset)
            pwm_out <= 0;
        else
            pwm_out <= (counter < duty_cycle);
    end
endmodule

FSM_Controller.v
// === fsm_controller.v ===
module fsm_controller #(
    parameter NUM_FLOORS = 10,
    parameter FLOOR_WIDTH = 4
)(
    input clk,
    input reset,
    input emergency_stop,
    input overweight,
    input door_obstruction,
    input [FLOOR_WIDTH-1:0] current_floor,
    input [NUM_FLOORS-1:0] floor_requests,
    input has_request_above,
    input has_request_below,

    output reg moving_up,
    output reg moving_down,
    output reg door_open,
    output reg clear_current_request,
    output reg [7:0] pwm_duty
);

    reg [3:0] state, next_state;
    reg [7:0] timer;

    localparam [3:0]
        IDLE            = 4'd0,
        CHECK_REQUEST   = 4'd1,
        MOVE_UP         = 4'd2,
        MOVE_DOWN       = 4'd3,
        OPEN_DOOR       = 4'd4,
        DOOR_WAIT       = 4'd5,
        CLOSE_DOOR      = 4'd6,
        EMERGENCY_STOP  = 4'd7,
        WAIT_FOR_WEIGHT = 4'd8;

    localparam DOOR_OPEN_TIME = 8'd50; 

    always @(posedge clk or posedge reset) begin
        if (reset)
            state <= IDLE;
        else
            state <= next_state;
    end

    always @(posedge clk or posedge reset) begin
        if (reset)
            timer <= 0;
        else if (state == DOOR_WAIT)
            timer <= timer + 1;
        else
            timer <= 0;
    end

  
    always @(*) begin
        moving_up = 0;
        moving_down = 0;
        door_open = 0;
        clear_current_request = 0;
        pwm_duty = 8'd0;

        case (state)
            MOVE_UP: begin
                moving_up = 1;
                pwm_duty = 8'd180;
            end
            MOVE_DOWN: begin
                moving_down = 1;
                pwm_duty = 8'd180;
            end
            OPEN_DOOR: begin
                door_open = 1;
                clear_current_request = 1;
            end
            DOOR_WAIT: door_open = 1;
            EMERGENCY_STOP: door_open = 1;
        endcase
    end

 
    always @(*) begin
        next_state = state;   // keep in current state by default   

        case (state)
            IDLE: begin
                if (emergency_stop)
                    next_state = EMERGENCY_STOP;
                else if (floor_requests != 0)
                    next_state = CHECK_REQUEST;
            end

            CHECK_REQUEST: begin
                if (emergency_stop)
                    next_state = EMERGENCY_STOP;
                else if (floor_requests[current_floor])
                    next_state = OPEN_DOOR;
                else if (has_request_above)
                    next_state = MOVE_UP;
                else if (has_request_below)
                    next_state = MOVE_DOWN;
                else
                    next_state = IDLE;
            end

            MOVE_UP, MOVE_DOWN: begin
                if (emergency_stop)
                    next_state = EMERGENCY_STOP;
                else if (overweight)
                    next_state = WAIT_FOR_WEIGHT;
                else if (floor_requests[current_floor])
                    next_state = OPEN_DOOR;
            end

            OPEN_DOOR: begin
                next_state = DOOR_WAIT;
            end

            DOOR_WAIT: begin
                if (door_obstruction)
                    next_state = DOOR_WAIT;
                else if (timer >= DOOR_OPEN_TIME)
                    next_state = CLOSE_DOOR;
            end

            CLOSE_DOOR: begin
                if (overweight)
                    next_state = WAIT_FOR_WEIGHT;
                else
                    next_state = CHECK_REQUEST;
            end

            WAIT_FOR_WEIGHT: begin
                if (!overweight)
                    next_state = CHECK_REQUEST;
            end

            EMERGENCY_STOP: begin
                if (!emergency_stop)
                    next_state = IDLE;
            end
        endcase
    end

endmodule

DirectionChecker.v
module direction_checker #(
    parameter NUM_FLOORS = 10,
    parameter FLOOR_WIDTH = 4
)(
    input [FLOOR_WIDTH-1:0] current_floor,
    input [NUM_FLOORS-1:0] floor_requests,
    output reg has_request_above,
    output reg has_request_below
);

    integer i;
    always @(*) begin
        has_request_above = 0;
        has_request_below = 0;
        for (i = 0; i < NUM_FLOORS; i = i + 1) begin
            if (i > current_floor && floor_requests[i])
                has_request_above = 1;
            if (i < current_floor && floor_requests[i])
                has_request_below = 1;
        end
    end

endmodule

requestHandler.v
module request_handler #(
    parameter NUM_FLOORS = 10,
    parameter FLOOR_WIDTH = 4
)(
    input clk,
    input reset,
    input [NUM_FLOORS-1:0] new_requests,
    input [FLOOR_WIDTH-1:0] current_floor,
    input clear_current_request,
    output reg [NUM_FLOORS-1:0] floor_requests
);

    always @(posedge clk or posedge reset) begin
        if (reset)
            floor_requests <= 0;
        else begin
            floor_requests <= floor_requests | new_requests;
            if (clear_current_request)
                floor_requests[current_floor] <= 0;
        end
    end

endmodule

FloorPositionDetector.v
module floor_position_detector #(
    parameter NUM_FLOORS = 10,
    parameter FLOOR_WIDTH = 4
)(
    input [NUM_FLOORS-1:0] floor_sensors,
    output reg [FLOOR_WIDTH-1:0] current_floor
);

    integer i;
    always @(*) begin
        current_floor = 0;
        for (i = 0; i < NUM_FLOORS; i = i + 1)
            if (floor_sensors[i])
                current_floor = i[FLOOR_WIDTH-1:0];
    end

endmodule

elevator_fsm_top.v
`include "DirectionChecker.v"
`include "FloorPositionDetector.v"
`include "requestHandler.v"
`include "FSM_Controller.v"
`include "PwmGenerator.v"
//========================================
//Kaushika M.K.I -EG/2021/4606            
//Sivanujan S - EG/2021/4816
//Senevirathne S.M.K.H.T - EG/2021/4806
//========================================

module elevator_fsm_top #(
    parameter NUM_FLOORS = 10,
    parameter FLOOR_WIDTH = 4
)(
    input clk,
    input reset,
    input emergency_stop,
    input overweight,
    input door_obstruction,
    input [NUM_FLOORS-1:0] new_requests,
    input [NUM_FLOORS-1:0] floor_sensors,

    output [NUM_FLOORS-1:0] floor_requests,
    output [FLOOR_WIDTH-1:0] current_floor,
    output moving_up,
    output moving_down,
    output door_open,
    output pwm_out
);

    wire [NUM_FLOORS-1:0] reqs;
    wire [FLOOR_WIDTH-1:0] floor;
    wire has_above, has_below;
    wire clear_request;
    wire [7:0] pwm_duty;

    assign floor_requests = reqs;
    assign current_floor = floor;

    floor_position_detector #(.NUM_FLOORS(NUM_FLOORS), .FLOOR_WIDTH(FLOOR_WIDTH)) detector (
        .floor_sensors(floor_sensors),
        .current_floor(floor)
    );

    request_handler #(.NUM_FLOORS(NUM_FLOORS), .FLOOR_WIDTH(FLOOR_WIDTH)) handler (
        .clk(clk),
        .reset(reset),
        .new_requests(new_requests),
        .current_floor(floor),
        .clear_current_request(clear_request),
        .floor_requests(reqs)
    );

    direction_checker #(.NUM_FLOORS(NUM_FLOORS), .FLOOR_WIDTH(FLOOR_WIDTH)) checker (
        .current_floor(floor),
        .floor_requests(reqs),
        .has_request_above(has_above),
        .has_request_below(has_below)
    );

    fsm_controller #(.NUM_FLOORS(NUM_FLOORS), .FLOOR_WIDTH(FLOOR_WIDTH)) controller (
        .clk(clk),
        .reset(reset),
        .emergency_stop(emergency_stop),
        .overweight(overweight),
        .door_obstruction(door_obstruction),
        .current_floor(floor),
        .floor_requests(reqs),
        .has_request_above(has_above),
        .has_request_below(has_below),
        .moving_up(moving_up),
        .moving_down(moving_down),
        .door_open(door_open),
        .clear_current_request(clear_request),
        .pwm_duty(pwm_duty)
    );

    pwm_generator pwm_unit (
        .clk(clk),
        .reset(reset),
        .duty_cycle(pwm_duty),
        .pwm_out(pwm_out)
    );

endmodule

Elevator_TOP_Tb.v
`timescale 1ns / 1ps
`include "elevator_fsm_top.v"

module elevator_fsm_top_tb;

    parameter NUM_FLOORS = 10;
    parameter FLOOR_WIDTH = 4;

    reg clk;
    reg reset;
    reg emergency_stop;
    reg overweight;
    reg door_obstruction;
    reg [NUM_FLOORS-1:0] new_requests;
    reg [NUM_FLOORS-1:0] floor_sensors;

    wire [NUM_FLOORS-1:0] floor_requests;
    wire [FLOOR_WIDTH-1:0] current_floor;
    wire moving_up;
    wire moving_down;
    wire door_open;
    wire pwm_out;

    // Instantiate the elevator top module
    elevator_fsm_top #(
        .NUM_FLOORS(NUM_FLOORS),
        .FLOOR_WIDTH(FLOOR_WIDTH)
    ) dut (
        .clk(clk),
        .reset(reset),
        .emergency_stop(emergency_stop),
        .overweight(overweight),
        .door_obstruction(door_obstruction),
        .new_requests(new_requests),
        .floor_sensors(floor_sensors),
        .floor_requests(floor_requests),
        .current_floor(current_floor),
        .moving_up(moving_up),
        .moving_down(moving_down),
        .door_open(door_open),
        .pwm_out(pwm_out)
    );

    // Clock generation
    initial clk = 0;
    always #5 clk = ~clk; // 100 MHz

    // VCD for GTKWave
    initial begin
        $dumpfile("elevator_fsm_top.vcd");
        $dumpvars(0, elevator_fsm_top_tb);
    end

    // Helper task to print a header
    task print_header;
        begin
            $display("\n---------------------------------------------------------------------------------------------------------------");
            $display("Time(ns) | Reset | EmStop | Overwt | DoorObs | CurrFloor | FloorReqs      | MovingUp | MovingDn | DoorOpen | ClearReq | PWM_Duty | PWM_Out");
            $display("---------------------------------------------------------------------------------------------------------------");
        end
    endtask

    // Helper task to simulate elevator at a given floor
    task set_floor(input [FLOOR_WIDTH-1:0] floor);
        begin
            floor_sensors = 0;
            floor_sensors[floor] = 1;
        end
    endtask

    // Signal change detection for clean printing
    reg [NUM_FLOORS-1:0] prev_floor_requests;
    reg [FLOOR_WIDTH-1:0] prev_floor;
    reg prev_moving_up, prev_moving_down, prev_door_open;
    reg prev_pwm_out;

    always @(posedge clk) begin
        if (reset || 
            prev_floor != current_floor || 
            prev_floor_requests != floor_requests || 
            prev_moving_up != moving_up || 
            prev_moving_down != moving_down || 
            prev_door_open != door_open || 
            prev_pwm_out != pwm_out) begin

            print_header();
            $display("%8d |   %b   |   %b    |   %b    |    %b    |    %2d     | %b |    %b    |    %b    |    %b    |    %b     |   %3d    |   %b",
                $time, reset, emergency_stop, overweight, door_obstruction,
                current_floor, floor_requests, moving_up, moving_down, door_open,
                dut.controller.clear_current_request, dut.controller.pwm_duty, pwm_out);
        end

        prev_floor = current_floor;
        prev_floor_requests = floor_requests;
        prev_moving_up = moving_up;
        prev_moving_down = moving_down;
        prev_door_open = door_open;
        prev_pwm_out = pwm_out;
    end

    initial begin
        $display("\n--- Simulation started ---");

        // === Initialization ===
        reset = 1;
        emergency_stop = 0;
        overweight = 0;
        door_obstruction = 0;
        new_requests = 0;
        floor_sensors = 0;

        #50;
        reset = 0;
        #50;

        set_floor(0); // Start at floor 0
        #200;

        // === Scenario 1 ===
        $display("\n>>> Scenario 1: Requests at floors 3, 5, 9");
        #100; new_requests[3] = 1; #100;
        new_requests[5] = 1; #100;
        new_requests[9] = 1; #100;
        new_requests = 0; #200;

        #200; set_floor(1); #200;
        #200; set_floor(2); #200;
        #200; set_floor(3); #800;

        #300; set_floor(4); #300;
        #300; set_floor(5); #800;

        #300; set_floor(6); #300;
        #300; set_floor(7); #300;
        #300; set_floor(8); #300;
        #300; set_floor(9); #800;

        // === Scenario 2 ===
        $display("\n>>> Scenario 2: Door Obstruction");
        door_obstruction = 1; #600;
        door_obstruction = 0; #400;

        // === Scenario 3 ===
        $display("\n>>> Scenario 3: Overweight Condition");
        overweight = 1; #600;
        overweight = 0; #400;

        // === Scenario 4 ===
        $display("\n>>> Scenario 4: Emergency Stop");
        emergency_stop = 1; #600;
        emergency_stop = 0; #400;

        // === Scenario 5 ===
        $display("\n>>> Scenario 5: Requests at floors 1 and 4");
        #200; new_requests[1] = 1; #200;
        new_requests[4] = 1; #100; new_requests = 0;

        #400; set_floor(8); #300;
        #300; set_floor(7); #300;
        #300; set_floor(6); #300;
        #300; set_floor(5); #300;
        #300; set_floor(4); #800;
        #300; set_floor(3); #300;
        #300; set_floor(2); #300;
        #300; set_floor(1); #800;

        $display("\n--- Simulation finished ---");
        $finish;
    end

endmodule

elevator_fsm_top.vcd
$date
	Fri Jul 04 14:52:01 2025
$end
$version
	Icarus Verilog
$end
$timescale
	1ps
$end
$scope module elevator_fsm_top_tb $end
$var wire 1 ! pwm_out $end
$var wire 1 " moving_up $end
$var wire 1 # moving_down $end
$var wire 10 $ floor_requests [9:0] $end
$var wire 1 % door_open $end
$var wire 4 & current_floor [3:0] $end
$var reg 1 ' clk $end
$var reg 1 ( door_obstruction $end
$var reg 1 ) emergency_stop $end
$var reg 10 * floor_sensors [9:0] $end
$var reg 10 + new_requests [9:0] $end
$var reg 1 , overweight $end
$var reg 1 - prev_door_open $end
$var reg 4 . prev_floor [3:0] $end
$var reg 10 / prev_floor_requests [9:0] $end
$var reg 1 0 prev_moving_down $end
$var reg 1 1 prev_moving_up $end
$var reg 1 2 prev_pwm_out $end
$var reg 1 3 reset $end
$scope module dut $end
$var wire 1 ' clk $end
$var wire 4 4 current_floor [3:0] $end
$var wire 1 ( door_obstruction $end
$var wire 1 ) emergency_stop $end
$var wire 10 5 floor_requests [9:0] $end
$var wire 10 6 floor_sensors [9:0] $end
$var wire 10 7 new_requests [9:0] $end
$var wire 1 , overweight $end
$var wire 1 3 reset $end
$var wire 10 8 reqs [9:0] $end
$var wire 1 ! pwm_out $end
$var wire 8 9 pwm_duty [7:0] $end
$var wire 1 " moving_up $end
$var wire 1 # moving_down $end
$var wire 1 : has_below $end
$var wire 1 ; has_above $end
$var wire 4 < floor [3:0] $end
$var wire 1 % door_open $end
$var wire 1 = clear_request $end
$scope module checker $end
$var wire 10 > floor_requests [9:0] $end
$var wire 4 ? current_floor [3:0] $end
$var reg 1 ; has_request_above $end
$var reg 1 : has_request_below $end
$var integer 32 @ i [31:0] $end
$upscope $end
$scope module controller $end
$var wire 1 ' clk $end
$var wire 1 ( door_obstruction $end
$var wire 1 ) emergency_stop $end
$var wire 1 ; has_request_above $end
$var wire 1 : has_request_below $end
$var wire 1 , overweight $end
$var wire 1 3 reset $end
$var wire 10 A floor_requests [9:0] $end
$var wire 4 B current_floor [3:0] $end
$var reg 1 = clear_current_request $end
$var reg 1 % door_open $end
$var reg 1 # moving_down $end
$var reg 1 " moving_up $end
$var reg 4 C next_state [3:0] $end
$var reg 8 D pwm_duty [7:0] $end
$var reg 4 E state [3:0] $end
$var reg 8 F timer [7:0] $end
$upscope $end
$scope module detector $end
$var wire 10 G floor_sensors [9:0] $end
$var reg 4 H current_floor [3:0] $end
$var integer 32 I i [31:0] $end
$upscope $end
$scope module handler $end
$var wire 1 = clear_current_request $end
$var wire 1 ' clk $end
$var wire 4 J current_floor [3:0] $end
$var wire 10 K new_requests [9:0] $end
$var wire 1 3 reset $end
$var reg 10 L floor_requests [9:0] $end
$upscope $end
$scope module pwm_unit $end
$var wire 1 ' clk $end
$var wire 8 M duty_cycle [7:0] $end
$var wire 1 3 reset $end
$var reg 8 N counter [7:0] $end
$var reg 1 ! pwm_out $end
$upscope $end
$upscope $end
$scope task print_header $end
$upscope $end
$scope task set_floor $end
$var reg 4 O floor [3:0] $end
$upscope $end
$upscope $end
$enddefinitions $end
#0
$dumpvars
bx O
b0 N
b0 M
b0 L
b0 K
b0 J
b1010 I
b0 H
b0 G
b0 F
b0 E
b0 D
b0 C
b0 B
b0 A
b1010 @
b0 ?
b0 >
0=
b0 <
0;
0:
b0 9
b0 8
b0 7
b0 6
b0 5
b0 4
13
x2
x1
x0
bx /
bx .
x-
0,
b0 +
b0 *
0)
0(
0'
b0 &
0%
b0 $
0#
0"
0!
$end
#5000
02
0-
00
01
b0 /
b0 .
1'
#10000
0'
#15000
1'
#20000
0'
#25000
1'
#30000
0'
#35000
1'
#40000
0'
#45000
1'
#50000
0'
03
#55000
b1 N
1'
#60000
0'
#65000
b10 N
1'
#70000
0'
#75000
b11 N
1'
#80000
0'
#85000
b100 N
1'
#90000
0'
#95000
b101 N
1'
#100000
b1010 I
0'
b1 *
b1 6
b1 G
b0 O
#105000
b110 N
1'
#110000
0'
#115000
b111 N
1'
#120000
0'
#125000
b1000 N
1'
#130000
0'
#135000
b1001 N
1'
#140000
0'
#145000
b1010 N
1'
#150000
0'
#155000
b1011 N
1'
#160000
0'
#165000
b1100 N
1'
#170000
0'
#175000
b1101 N
1'
#180000
0'
#185000
b1110 N
1'
#190000
0'
#195000
b1111 N
1'
#200000
0'
#205000
b10000 N
1'
#210000
0'
#215000
b10001 N
1'
#220000
0'
#225000
b10010 N
1'
#230000
0'
#235000
b10011 N
1'
#240000
0'
#245000
b10100 N
1'
#250000
0'
#255000
b10101 N
1'
#260000
0'
#265000
b10110 N
1'
#270000
0'
#275000
b10111 N
1'
#280000
0'
#285000
b11000 N
1'
#290000
0'
#295000
b11001 N
1'
#300000
0'
#305000
b11010 N
1'
#310000
0'
#315000
b11011 N
1'
#320000
0'
#325000
b11100 N
1'
#330000
0'
#335000
b11101 N
1'
#340000
0'
#345000
b11110 N
1'
#350000
0'
#355000
b11111 N
1'
#360000
0'
#365000
b100000 N
1'
#370000
0'
#375000
b100001 N
1'
#380000
0'
#385000
b100010 N
1'
#390000
0'
#395000
b100011 N
1'
#400000
0'
b1000 +
b1000 7
b1000 K
#405000
1;
b1010 @
b1 C
b100100 N
b1000 $
b1000 5
b1000 8
b1000 >
b1000 A
b1000 L
1'
#410000
0'
#415000
b10 C
b1 E
b100101 N
b1000 /
1'
#420000
0'
#425000
b10110100 9
b10110100 D
b10110100 M
1"
b100110 N
b10 E
1'
#430000
0'
#435000
b100111 N
1!
11
1'
#440000
0'
#445000
b101000 N
12
1'
#450000
0'
#455000
b101001 N
1'
#460000
0'
#465000
b101010 N
1'
#470000
0'
#475000
b101011 N
1'
#480000
0'
#485000
b101100 N
1'
#490000
0'
#495000
b101101 N
1'
#500000
0'
b101000 +
b101000 7
b101000 K
#505000
b1010 @
1;
b101110 N
b101000 $
b101000 5
b101000 8
b101000 >
b101000 A
b101000 L
1'
#510000
0'
#515000
b101111 N
b101000 /
1'
#520000
0'
#525000
b110000 N
1'
#530000
0'
#535000
b110001 N
1'
#540000
0'
#545000
b110010 N
1'
#550000
0'
#555000
b110011 N
1'
#560000
0'
#565000
b110100 N
1'
#570000
0'
#575000
b110101 N
1'
#580000
0'
#585000
b110110 N
1'
#590000
0'
#595000
b110111 N
1'
#600000
0'
b1000101000 +
b1000101000 7
b1000101000 K
#605000
b1010 @
1;
b111000 N
b1000101000 $
b1000101000 5
b1000101000 8
b1000101000 >
b1000101000 A
b1000101000 L
1'
#610000
0'
#615000
b111001 N
b1000101000 /
1'
#620000
0'
#625000
b111010 N
1'
#630000
0'
#635000
b111011 N
1'
#640000
0'
#645000
b111100 N
1'
#650000
0'
#655000
b111101 N
1'
#660000
0'
#665000
b111110 N
1'
#670000
0'
#675000
b111111 N
1'
#680000
0'
#685000
b1000000 N
1'
#690000
0'
#695000
b1000001 N
1'
#700000
0'
b0 +
b0 7
b0 K
#705000
b1000010 N
1'
#710000
0'
#715000
b1000011 N
1'
#720000
0'
#725000
b1000100 N
1'
#730000
0'
#735000
b1000101 N
1'
#740000
0'
#745000
b1000110 N
1'
#750000
0'
#755000
b1000111 N
1'
#760000
0'
#765000
b1001000 N
1'
#770000
0'
#775000
b1001001 N
1'
#780000
0'
#785000
b1001010 N
1'
#790000
0'
#795000
b1001011 N
1'
#800000
0'
#805000
b1001100 N
1'
#810000
0'
#815000
b1001101 N
1'
#820000
0'
#825000
b1001110 N
1'
#830000
0'
#835000
b1001111 N
1'
#840000
0'
#845000
b1010000 N
1'
#850000
0'
#855000
b1010001 N
1'
#860000
0'
#865000
b1010010 N
1'
#870000
0'
#875000
b1010011 N
1'
#880000
0'
#885000
b1010100 N
1'
#890000
0'
#895000
b1010101 N
1'
#900000
0'
#905000
b1010110 N
1'
#910000
0'
#915000
b1010111 N
1'
#920000
0'
#925000
b1011000 N
1'
#930000
0'
#935000
b1011001 N
1'
#940000
0'
#945000
b1011010 N
1'
#950000
0'
#955000
b1011011 N
1'
#960000
0'
#965000
b1011100 N
1'
#970000
0'
#975000
b1011101 N
1'
#980000
0'
#985000
b1011110 N
1'
#990000
0'
#995000
b1011111 N
1'
#1000000
0'
#1005000
b1100000 N
1'
#1010000
0'
#1015000
b1100001 N
1'
#1020000
0'
#1025000
b1100010 N
1'
#1030000
0'
#1035000
b1100011 N
1'
#1040000
0'
#1045000
b1100100 N
1'
#1050000
0'
#1055000
b1100101 N
1'
#1060000
0'
#1065000
b1100110 N
1'
#1070000
0'
#1075000
b1100111 N
1'
#1080000
0'
#1085000
b1101000 N
1'
#1090000
0'
#1095000
b1101001 N
1'
#1100000
b1010 @
1;
b1 &
b1 4
b1 <
b1 ?
b1 B
b1 H
b1 J
b1010 I
0'
b10 *
b10 6
b10 G
b1 O
#1105000
b1101010 N
b1 .
1'
#1110000
0'
#1115000
b1101011 N
1'
#1120000
0'
#1125000
b1101100 N
1'
#1130000
0'
#1135000
b1101101 N
1'
#1140000
0'
#1145000
b1101110 N
1'
#1150000
0'
#1155000
b1101111 N
1'
#1160000
0'
#1165000
b1110000 N
1'
#1170000
0'
#1175000
b1110001 N
1'
#1180000
0'
#1185000
b1110010 N
1'
#1190000
0'
#1195000
b1110011 N
1'
#1200000
0'
#1205000
b1110100 N
1'
#1210000
0'
#1215000
b1110101 N
1'
#1220000
0'
#1225000
b1110110 N
1'
#1230000
0'
#1235000
b1110111 N
1'
#1240000
0'
#1245000
b1111000 N
1'
#1250000
0'
#1255000
b1111001 N
1'
#1260000
0'
#1265000
b1111010 N
1'
#1270000
0'
#1275000
b1111011 N
1'
#1280000
0'
#1285000
b1111100 N
1'
#1290000
0'
#1295000
b1111101 N
1'
#1300000
0'
#1305000
b1111110 N
1'
#1310000
0'
#1315000
b1111111 N
1'
#1320000
0'
#1325000
b10000000 N
1'
#1330000
0'
#1335000
b10000001 N
1'
#1340000
0'
#1345000
b10000010 N
1'
#1350000
0'
#1355000
b10000011 N
1'
#1360000
0'
#1365000
b10000100 N
1'
#1370000
0'
#1375000
b10000101 N
1'
#1380000
0'
#1385000
b10000110 N
1'
#1390000
0'
#1395000
b10000111 N
1'
#1400000
0'
#1405000
b10001000 N
1'
#1410000
0'
#1415000
b10001001 N
1'
#1420000
0'
#1425000
b10001010 N
1'
#1430000
0'
#1435000
b10001011 N
1'
#1440000
0'
#1445000
b10001100 N
1'
#1450000
0'
#1455000
b10001101 N
1'
#1460000
0'
#1465000
b10001110 N
1'
#1470000
0'
#1475000
b10001111 N
1'
#1480000
0'
#1485000
b10010000 N
1'
#1490000
0'
#1495000
b10010001 N
1'
#1500000
b1010 @
1;
b1010 I
b10 &
b10 4
b10 <
b10 ?
b10 B
b10 H
b10 J
0'
b100 *
b100 6
b100 G
b10 O
#1505000
b10010010 N
b10 .
1'
#1510000
0'
#1515000
b10010011 N
1'
#1520000
0'
#1525000
b10010100 N
1'
#1530000
0'
#1535000
b10010101 N
1'
#1540000
0'
#1545000
b10010110 N
1'
#1550000
0'
#1555000
b10010111 N
1'
#1560000
0'
#1565000
b10011000 N
1'
#1570000
0'
#1575000
b10011001 N
1'
#1580000
0'
#1585000
b10011010 N
1'
#1590000
0'
#1595000
b10011011 N
1'
#1600000
0'
#1605000
b10011100 N
1'
#1610000
0'
#1615000
b10011101 N
1'
#1620000
0'
#1625000
b10011110 N
1'
#1630000
0'
#1635000
b10011111 N
1'
#1640000
0'
#1645000
b10100000 N
1'
#1650000
0'
#1655000
b10100001 N
1'
#1660000
0'
#1665000
b10100010 N
1'
#1670000
0'
#1675000
b10100011 N
1'
#1680000
0'
#1685000
b10100100 N
1'
#1690000
0'
#1695000
b10100101 N
1'
#1700000
0'
#1705000
b10100110 N
1'
#1710000
0'
#1715000
b10100111 N
1'
#1720000
0'
#1725000
b10101000 N
1'
#1730000
0'
#1735000
b10101001 N
1'
#1740000
0'
#1745000
b10101010 N
1'
#1750000
0'
#1755000
b10101011 N
1'
#1760000
0'
#1765000
b10101100 N
1'
#1770000
0'
#1775000
b10101101 N
1'
#1780000
0'
#1785000
b10101110 N
1'
#1790000
0'
#1795000
b10101111 N
1'
#1800000
0'
#1805000
b10110000 N
1'
#1810000
0'
#1815000
b10110001 N
1'
#1820000
0'
#1825000
b10110010 N
1'
#1830000
0'
#1835000
b10110011 N
1'
#1840000
0'
#1845000
b10110100 N
1'
#1850000
0'
#1855000
b10110101 N
0!
1'
#1860000
0'
#1865000
b10110110 N
02
1'
#1870000
0'
#1875000
b10110111 N
1'
#1880000
0'
#1885000
b10111000 N
1'
#1890000
0'
#1895000
b10111001 N
1'
#1900000
b1010 @
1;
b100 C
b1010 I
b11 &
b11 4
b11 <
b11 ?
b11 B
b11 H
b11 J
0'
b1000 *
b1000 6
b1000 G
b11 O
#1905000
b101 C
1=
1%
b0 9
b0 D
b0 M
0"
b10111010 N
b100 E
b11 .
1'
#1910000
0'
#1915000
b1010 @
1;
0=
1%
b1000100000 $
b1000100000 5
b1000100000 8
b1000100000 >
b1000100000 A
b1000100000 L
b101 E
b10111011 N
1-
01
1'
#1920000
0'
#1925000
b10111100 N
b1 F
b1000100000 /
1'
#1930000
0'
#1935000
b10 F
b10111101 N
1'
#1940000
0'
#1945000
b10111110 N
b11 F
1'
#1950000
0'
#1955000
b100 F
b10111111 N
1'
#1960000
0'
#1965000
b11000000 N
b101 F
1'
#1970000
0'
#1975000
b110 F
b11000001 N
1'
#1980000
0'
#1985000
b11000010 N
b111 F
1'
#1990000
0'
#1995000
b1000 F
b11000011 N
1'
#2000000
0'
#2005000
b11000100 N
b1001 F
1'
#2010000
0'
#2015000
b1010 F
b11000101 N
1'
#2020000
0'
#2025000
b11000110 N
b1011 F
1'
#2030000
0'
#2035000
b1100 F
b11000111 N
1'
#2040000
0'
#2045000
b11001000 N
b1101 F
1'
#2050000
0'
#2055000
b1110 F
b11001001 N
1'
#2060000
0'
#2065000
b11001010 N
b1111 F
1'
#2070000
0'
#2075000
b10000 F
b11001011 N
1'
#2080000
0'
#2085000
b11001100 N
b10001 F
1'
#2090000
0'
#2095000
b10010 F
b11001101 N
1'
#2100000
0'
#2105000
b11001110 N
b10011 F
1'
#2110000
0'
#2115000
b10100 F
b11001111 N
1'
#2120000
0'
#2125000
b11010000 N
b10101 F
1'
#2130000
0'
#2135000
b10110 F
b11010001 N
1'
#2140000
0'
#2145000
b11010010 N
b10111 F
1'
#2150000
0'
#2155000
b11000 F
b11010011 N
1'
#2160000
0'
#2165000
b11010100 N
b11001 F
1'
#2170000
0'
#2175000
b11010 F
b11010101 N
1'
#2180000
0'
#2185000
b11010110 N
b11011 F
1'
#2190000
0'
#2195000
b11100 F
b11010111 N
1'
#2200000
0'
#2205000
b11011000 N
b11101 F
1'
#2210000
0'
#2215000
b11110 F
b11011001 N
1'
#2220000
0'
#2225000
b11011010 N
b11111 F
1'
#2230000
0'
#2235000
b100000 F
b11011011 N
1'
#2240000
0'
#2245000
b11011100 N
b100001 F
1'
#2250000
0'
#2255000
b100010 F
b11011101 N
1'
#2260000
0'
#2265000
b11011110 N
b100011 F
1'
#2270000
0'
#2275000
b100100 F
b11011111 N
1'
#2280000
0'
#2285000
b11100000 N
b100101 F
1'
#2290000
0'
#2295000
b100110 F
b11100001 N
1'
#2300000
0'
#2305000
b11100010 N
b100111 F
1'
#2310000
0'
#2315000
b101000 F
b11100011 N
1'
#2320000
0'
#2325000
b11100100 N
b101001 F
1'
#2330000
0'
#2335000
b101010 F
b11100101 N
1'
#2340000
0'
#2345000
b11100110 N
b101011 F
1'
#2350000
0'
#2355000
b101100 F
b11100111 N
1'
#2360000
0'
#2365000
b11101000 N
b101101 F
1'
#2370000
0'
#2375000
b101110 F
b11101001 N
1'
#2380000
0'
#2385000
b11101010 N
b101111 F
1'
#2390000
0'
#2395000
b110000 F
b11101011 N
1'
#2400000
0'
#2405000
b11101100 N
b110001 F
1'
#2410000
0'
#2415000
b110 C
b110010 F
b11101101 N
1'
#2420000
0'
#2425000
b1 C
0%
b11101110 N
b110011 F
b110 E
1'
#2430000
0'
#2435000
b10 C
b1 E
b0 F
b11101111 N
0-
1'
#2440000
0'
#2445000
b10110100 9
b10110100 D
b10110100 M
1"
b11110000 N
b10 E
1'
#2450000
0'
#2455000
b11110001 N
11
1'
#2460000
0'
#2465000
b11110010 N
1'
#2470000
0'
#2475000
b11110011 N
1'
#2480000
0'
#2485000
b11110100 N
1'
#2490000
0'
#2495000
b11110101 N
1'
#2500000
0'
#2505000
b11110110 N
1'
#2510000
0'
#2515000
b11110111 N
1'
#2520000
0'
#2525000
b11111000 N
1'
#2530000
0'
#2535000
b11111001 N
1'
#2540000
0'
#2545000
b11111010 N
1'
#2550000
0'
#2555000
b11111011 N
1'
#2560000
0'
#2565000
b11111100 N
1'
#2570000
0'
#2575000
b11111101 N
1'
#2580000
0'
#2585000
b11111110 N
1'
#2590000
0'
#2595000
b11111111 N
1'
#2600000
0'
#2605000
b0 N
1'
#2610000
0'
#2615000
b1 N
1!
1'
#2620000
0'
#2625000
b10 N
12
1'
#2630000
0'
#2635000
b11 N
1'
#2640000
0'
#2645000
b100 N
1'
#2650000
0'
#2655000
b101 N
1'
#2660000
0'
#2665000
b110 N
1'
#2670000
0'
#2675000
b111 N
1'
#2680000
0'
#2685000
b1000 N
1'
#2690000
0'
#2695000
b1001 N
1'
#2700000
0'
#2705000
b1010 N
1'
#2710000
0'
#2715000
b1011 N
1'
#2720000
0'
#2725000
b1100 N
1'
#2730000
0'
#2735000
b1101 N
1'
#2740000
0'
#2745000
b1110 N
1'
#2750000
0'
#2755000
b1111 N
1'
#2760000
0'
#2765000
b10000 N
1'
#2770000
0'
#2775000
b10001 N
1'
#2780000
0'
#2785000
b10010 N
1'
#2790000
0'
#2795000
b10011 N
1'
#2800000
0'
#2805000
b10100 N
1'
#2810000
0'
#2815000
b10101 N
1'
#2820000
0'
#2825000
b10110 N
1'
#2830000
0'
#2835000
b10111 N
1'
#2840000
0'
#2845000
b11000 N
1'
#2850000
0'
#2855000
b11001 N
1'
#2860000
0'
#2865000
b11010 N
1'
#2870000
0'
#2875000
b11011 N
1'
#2880000
0'
#2885000
b11100 N
1'
#2890000
0'
#2895000
b11101 N
1'
#2900000
0'
#2905000
b11110 N
1'
#2910000
0'
