FloorPositionDetector.v
module floor_position_detector #(
    parameter NUM_FLOORS = 10,
    parameter FLOOR_WIDTH = 4
)(
    input [NUM_FLOORS-1:0] floor_sensors,
    output reg [FLOOR_WIDTH-1:0] current_floor
);

    integer i;
    always @(*) begin
        current_floor = 0;
        for (i = 0; i < NUM_FLOORS; i = i + 1)
            if (floor_sensors[i])
                current_floor = i[FLOOR_WIDTH-1:0];
    end

endmodule

FloorPositionDetewctorTB.v
`timescale 1ns / 1ps
`include "FloorPositionDetector.v  "

module floor_position_detector_tb;

    // Parameters
    parameter NUM_FLOORS = 10;
    parameter FLOOR_WIDTH = 4;

    // Inputs
    reg [NUM_FLOORS-1:0] floor_sensors;

    // Outputs
    wire [FLOOR_WIDTH-1:0] current_floor;

    // Instantiate the Unit Under Test (UUT)
    floor_position_detector #(
        .NUM_FLOORS(NUM_FLOORS),
        .FLOOR_WIDTH(FLOOR_WIDTH)
    ) uut (
        .floor_sensors(floor_sensors),
        .current_floor(current_floor)
    );

    // VCD dump for GTKWave
    initial begin
        $dumpfile("floor_position_detector.vcd");
        $dumpvars(0, floor_position_detector_tb);
    end

    // Test sequence
    initial begin
        $display("Time\tSensor Input\tDetected Floor");
        
        // Test each floor one by one
        floor_sensors = 10'b0000000001; // Floor 0
        #10 $display("%0t\t%b\t%d", $time, floor_sensors, current_floor);

        floor_sensors = 10'b0000000010; // Floor 1
        #10 $display("%0t\t%b\t%d", $time, floor_sensors, current_floor);

        floor_sensors = 10'b0000000100; // Floor 2
        #10 $display("%0t\t%b\t%d", $time, floor_sensors, current_floor);

        floor_sensors = 10'b0000001000; // Floor 3
        #10 $display("%0t\t%b\t%d", $time, floor_sensors, current_floor);

        floor_sensors = 10'b0000010000; // Floor 4
        #10 $display("%0t\t%b\t%d", $time, floor_sensors, current_floor);

        floor_sensors = 10'b0000100000; // Floor 5
        #10 $display("%0t\t%b\t%d", $time, floor_sensors, current_floor);

        floor_sensors = 10'b0001000000; // Floor 6
        #10 $display("%0t\t%b\t%d", $time, floor_sensors, current_floor);

        floor_sensors = 10'b0010000000; // Floor 7
        #10 $display("%0t\t%b\t%d", $time, floor_sensors, current_floor);

        floor_sensors = 10'b0100000000; // Floor 8
        #10 $display("%0t\t%b\t%d", $time, floor_sensors, current_floor);

        floor_sensors = 10'b1000000000; // Floor 9
        #10 $display("%0t\t%b\t%d", $time, floor_sensors, current_floor);

        // Multiple sensors active (e.g., noise or glitch)
        floor_sensors = 10'b0000100100; // Floor 5 and 2 active → should detect highest (5)
        #10 $display("%0t\t%b\t%d", $time, floor_sensors, current_floor);

        // No sensor active (invalid case)
        floor_sensors = 10'b0000000000;
        #10 $display("%0t\t%b\t%d", $time, floor_sensors, current_floor);

        #20 $finish;
    end

endmodule

floor_position_detector.vcd
$date
	Fri Jul 04 10:56:46 2025
$end
$version
	Icarus Verilog
$end
$timescale
	1ps
$end
$scope module floor_position_detector_tb $end
$var wire 4 ! current_floor [3:0] $end
$var reg 10 " floor_sensors [9:0] $end
$scope module uut $end
$var wire 10 # floor_sensors [9:0] $end
$var reg 4 $ current_floor [3:0] $end
$var integer 32 % i [31:0] $end
$upscope $end
$upscope $end
$enddefinitions $end
#0
$dumpvars
b1010 %
b0 $
b1 #
b1 "
b0 !
$end
#10000
b1 !
b1 $
b1010 %
b10 "
b10 #
#20000
b1010 %
b10 !
b10 $
b100 "
b100 #
#30000
b1010 %
b11 !
b11 $
b1000 "
b1000 #
#40000
b1010 %
b100 !
b100 $
b10000 "
b10000 #
#50000
b1010 %
b101 !
b101 $
b100000 "
b100000 #
#60000
b1010 %
b110 !
b110 $
b1000000 "
b1000000 #
#70000
b1010 %
b111 !
b111 $
b10000000 "
b10000000 #
#80000
b1010 %
b1000 !
b1000 $
b100000000 "
b100000000 #
#90000
b1010 %
b1001 !
b1001 $
b1000000000 "
b1000000000 #
#100000
b1010 %
b101 !
b101 $
b100100 "
b100100 #
#110000
b1010 %
b0 !
b0 $
b0 "
b0 #
