requestHandler.v
module request_handler #(
    parameter NUM_FLOORS = 10,
    parameter FLOOR_WIDTH = 4
)(
    input clk,
    input reset,
    input [NUM_FLOORS-1:0] new_requests,
    input [FLOOR_WIDTH-1:0] current_floor,
    input clear_current_request,
    output reg [NUM_FLOORS-1:0] floor_requests
);

    always @(posedge clk or posedge reset) begin
        if (reset)
            floor_requests <= 0;
        else begin
            floor_requests <= floor_requests | new_requests;
            if (clear_current_request)
                floor_requests[current_floor] <= 0;
        end
    end

endmodule

requestHandlerTB.v
`timescale 1ns / 1ps
`include "RequestHandler.v"

module request_handler_tb;

    parameter NUM_FLOORS = 10;
    parameter FLOOR_WIDTH = 4;

    reg clk, reset;
    reg [NUM_FLOORS-1:0] new_requests;
    reg [FLOOR_WIDTH-1:0] current_floor;
    reg clear_current_request;

    wire [NUM_FLOORS-1:0] floor_requests;

    // Instantiate DUT
    request_handler #(
        .NUM_FLOORS(NUM_FLOORS),
        .FLOOR_WIDTH(FLOOR_WIDTH)
    ) dut (
        .clk(clk),
        .reset(reset),
        .new_requests(new_requests),
        .current_floor(current_floor),
        .clear_current_request(clear_current_request),
        .floor_requests(floor_requests)
    );

    // Clock generation: 10ns period
    initial clk = 0;
    always #5 clk = ~clk;

    // Monitor output
    initial begin
        $display("Time\tReset\tNewReq\tCurrentFloor\tClear\tFloorRequests");
        $monitor("%0t\t%b\t%b\t%d\t\t%b\t%b", 
                 $time, reset, new_requests, current_floor, clear_current_request, floor_requests);
    end

    // VCD dump for GTKWave
    initial begin
        $dumpfile("request_handler.vcd");
        $dumpvars(0, request_handler_tb);
    end

    initial begin
    // Initialize signals
    reset = 1; new_requests = 0; current_floor = 0; clear_current_request = 0;
    #20 reset = 0;

    // Starting floor = 1
    current_floor = 1;

    // Requests at floors 2,4,5,9
    new_requests = 10'b1001100100; 
    // Binary bit indices: floor9=1, floor5=1, floor4=1, floor2=1
    // (bits counted from 0 = floor0 to 9 = floor9)
    #10 new_requests = 0; // Clear new_requests after latching

    // Check requests remain
    #20;

    // Move elevator through floors 2,4,5 (simulate but no clear)
    current_floor = 2;
    #50 current_floor = 4;
    #50 current_floor = 5;

    // Floor 9 reached - clear floor 9 request
    #50 current_floor = 9;
    clear_current_request = 1;
    #10 clear_current_request = 0;

    // Check remaining requests still set at 2,4,5
    #50;

    $finish;
end

endmodule

request_handler.vcd
$date
	Fri Jul 04 11:11:17 2025
$end
$version
	Icarus Verilog
$end
$timescale
	1ps
$end
$scope module request_handler_tb $end
$var wire 10 ! floor_requests [9:0] $end
$var reg 1 " clear_current_request $end
$var reg 1 # clk $end
$var reg 4 $ current_floor [3:0] $end
$var reg 10 % new_requests [9:0] $end
$var reg 1 & reset $end
$scope module dut $end
$var wire 1 " clear_current_request $end
$var wire 1 # clk $end
$var wire 4 ' current_floor [3:0] $end
$var wire 10 ( new_requests [9:0] $end
$var wire 1 & reset $end
$var reg 10 ) floor_requests [9:0] $end
$upscope $end
$upscope $end
$enddefinitions $end
#0
$dumpvars
b0 )
b0 (
b0 '
1&
b0 %
b0 $
0#
0"
b0 !
$end
#5000
1#
#10000
0#
#15000
1#
#20000
0#
b1001100100 %
b1001100100 (
b1 $
b1 '
0&
#25000
b1001100100 !
b1001100100 )
1#
#30000
0#
b0 %
b0 (
#35000
1#
#40000
0#
#45000
1#
#50000
0#
b10 $
b10 '
#55000
1#
#60000
0#
#65000
1#
#70000
0#
#75000
1#
#80000
0#
#85000
1#
#90000
0#
#95000
1#
#100000
0#
b100 $
b100 '
#105000
1#
#110000
0#
#115000
1#
#120000
0#
#125000
1#
#130000
0#
#135000
1#
#140000
0#
#145000
1#
#150000
0#
b101 $
b101 '
#155000
1#
#160000
0#
#165000
1#
#170000
0#
#175000
1#
#180000
0#
#185000
1#
#190000
0#
#195000
1#
#200000
0#
1"
b1001 $
b1001 '
#205000
b1100100 !
b1100100 )
1#
#210000
0#
0"
